dimensia/__init__.py
dimensia/dimensia.py
dimensia/exceptions.py
dimensia/utils.py
dimensia-0.1.3.dist-info/LICENSE
dimensia-0.1.3.dist-info/METADATA
dimensia-0.1.3.dist-info/WHEEL
dimensia-0.1.3.dist-info/top_level.txt
dimensia-0.1.3.dist-info/RECORD
