Metadata-Version: 2.1
Name: dimensia
Version: 0.1.3
Summary: Dimensia is a Python library for managing document embeddings and performing efficient similarity-based searches using various distance metrics.
Home-page: https://github.com/aniruddhasalve/dimensia
Author: Aniruddha Salve
Author-email: salveaniruddha180@gmail.com
License: MIT License
Project-URL: Homepage, https://github.com/aniruddhasalve/dimensia
Project-URL: Bug Tracker, https://github.com/aniruddhasalve/dimensia/issues
Project-URL: Source Code, https://github.com/aniruddhasalve/dimensia
Keywords: vector,database,embeddings,NLP,AI,search
Classifier: Programming Language :: Python :: 3
Classifier: License :: OSI Approved :: MIT License
Classifier: Operating System :: OS Independent
Classifier: Programming Language :: Python :: 3.6
Classifier: Programming Language :: Python :: 3.7
Classifier: Programming Language :: Python :: 3.8
Classifier: Programming Language :: Python :: 3.9
Classifier: Intended Audience :: Developers
Classifier: Topic :: Software Development :: Libraries :: Python Modules
Requires-Python: >=3.6
License-File: LICENSE
Requires-Dist: sentence-transformers
Requires-Dist: tqdm
Requires-Dist: numpy
Requires-Dist: requests
